{
  "project_info": {
    "project_number": "164566727064",
    "project_id": "projectgd-386307",
    "storage_bucket": "projectgd-386307.appspot.com"
  },
  "client": [
    {
      "client_info": {
        "mobilesdk_app_id": "1:164566727064:android:03c53ad62932c639ffd3ed",
        "android_client_info": {
          "package_name": "com.dongminpark.projectgd"
        }
      },
      "oauth_client": [
        {
          "client_id": "164566727064-hnrrd7k7ai58ljea0kpjtco1nq778ovc.apps.googleusercontent.com",
          "client_type": 1,
          "android_info": {
            "package_name": "com.dongminpark.projectgd",
            "certificate_hash": "d96210027e3f8e0fb91b84ad07f32a8f15dd2a66"
          }
        }
      ],
      "api_key": [
        {
          "current_key": "AIzaSyDbmBkzApGmf9xvUMsq2sP0DK8Lz3TbHGQ"
        }
      ],
      "services": {
        "appinvite_service": {
          "other_platform_oauth_client": [
            {
              "client_id": "164566727064-ldq29hf1m3klv9rb3eukt53d9qdfn7jp.apps.googleusercontent.com",
              "client_type": 3
            }
          ]
        }
      }
    },
    {
      "client_info": {
        "mobilesdk_app_id": "1:164566727064:android:a2d7d5fd50de31dcffd3ed",
        "android_client_info": {
          "package_name": "com.example.gd"
        }
      },
      "oauth_client": [],
      "api_key": [
        {
          "current_key": "AIzaSyDbmBkzApGmf9xvUMsq2sP0DK8Lz3TbHGQ"
        }
      ],
      "services": {
        "appinvite_service": {
          "other_platform_oauth_client": [
            {
              "client_id": "164566727064-ldq29hf1m3klv9rb3eukt53d9qdfn7jp.apps.googleusercontent.com",
              "client_type": 3
            }
          ]
        }
      }
    }
  ],
  "configuration_version": "1"
}